setup.py
ngrok/__init__.py
ngrok/client.py
ngrok/link.py
python_ngrok.egg-info/PKG-INFO
python_ngrok.egg-info/SOURCES.txt
python_ngrok.egg-info/dependency_links.txt
python_ngrok.egg-info/top_level.txt