Metadata-Version: 1.1
Name: python-ngrok
Version: 0.1
Summary: Python bindings for ngrok local and Link APIs
Home-page: https://git.coderouge.co/coderouge/python-ngrok
Author: Jacob Cook
Author-email: jacob@coderouge.co
License: GPLv3
Download-URL: https://git.coderouge.co/coderouge/python-ngrok/repository/archive.tar.gz?ref=0.1
Platform: UNKNOWN
